panoramic/cli/__init__.py
panoramic/cli/__main__.py
panoramic/cli/__version__.py
panoramic/cli/cli.py
panoramic/cli/command.py
panoramic/cli/connection.py
panoramic/cli/controller.py
panoramic/cli/diff.py
panoramic/cli/errors.py
panoramic/cli/executor.py
panoramic/cli/file_utils.py
panoramic/cli/pano_model.py
panoramic/cli/paths.py
panoramic/cli/print.py
panoramic/cli/py.typed
panoramic/cli/scan.py
panoramic/cli/state.py
panoramic/cli/supported_version.py
panoramic/cli/validate.py
panoramic/cli/config/__init__.py
panoramic/cli/config/companies.py
panoramic/cli/config/storage.py
panoramic/cli/datacol/__init__.py
panoramic/cli/datacol/py.typed
panoramic/cli/datacol/tztools.py
panoramic/cli/husky/__init__.py
panoramic/cli/husky/common/__init__.py
panoramic/cli/husky/common/enum.py
panoramic/cli/husky/common/exception_enums.py
panoramic/cli/husky/common/exception_handler.py
panoramic/cli/husky/common/my_memoize.py
panoramic/cli/husky/common/sqlalchemy_ext.py
panoramic/cli/husky/common/util.py
panoramic/cli/husky/core/__init__.py
panoramic/cli/husky/core/enums.py
panoramic/cli/husky/core/errors.py
panoramic/cli/husky/core/sql_alchemy_util.py
panoramic/cli/husky/core/util.py
panoramic/cli/husky/core/federated/__init__.py
panoramic/cli/husky/core/federated/utils.py
panoramic/cli/husky/core/federated/model/__init__.py
panoramic/cli/husky/core/federated/model/exceptions.py
panoramic/cli/husky/core/federated/model/mappers.py
panoramic/cli/husky/core/federated/model/models.py
panoramic/cli/husky/core/federated/model/tel/__init__.py
panoramic/cli/husky/core/federated/model/tel/data_structures.py
panoramic/cli/husky/core/federated/model/tel/exceptions.py
panoramic/cli/husky/core/federated/model/tel/visitor.py
panoramic/cli/husky/core/federated/taxonomy/__init__.py
panoramic/cli/husky/core/federated/taxonomy/mapper.py
panoramic/cli/husky/core/federated/transform/__init__.py
panoramic/cli/husky/core/federated/transform/models.py
panoramic/cli/husky/core/model/__init__.py
pano-2.1.0.dist-info/LICENSE
pano-2.1.0.dist-info/METADATA
pano-2.1.0.dist-info/WHEEL
pano-2.1.0.dist-info/entry_points.txt
pano-2.1.0.dist-info/top_level.txt
pano-2.1.0.dist-info/RECORD
