Metadata-Version: 2.1
Name: pano
Version: 2.1.0
Summary: Panoramic Command Line Tool
Home-page: https://github.com/panoramichq/panoramic-cli
Author: Panoramic
Maintainer: Panoramic
License: UNKNOWN
Project-URL: Source Code, https://github.com/panoramichq/panoramic-cli
Platform: UNKNOWN
Classifier: Development Status :: 5 - Production/Stable
Classifier: License :: OSI Approved
Classifier: License :: OSI Approved :: MIT License
Classifier: Programming Language :: Python :: 3
Classifier: Programming Language :: Python :: 3.7
Classifier: Programming Language :: Python :: 3.8
Requires-Python: >=3.6
Requires-Dist: click (>=7.1.2)
Requires-Dist: colorama (>=0.4.3)
Requires-Dist: PyYAML (==5.3.1)
Requires-Dist: packaging (>=20.4)
Requires-Dist: tqdm (==4.47.0)
Requires-Dist: python-dotenv (>=0.14.0)
Requires-Dist: jsonschema (>=3.0)
Requires-Dist: requests (>=2.18.0)
Requires-Dist: analytics-python (==1.2.9)
Requires-Dist: sqlalchemy (>=1.3.19)
Requires-Dist: snowflake-sqlalchemy (==1.2.3)
Requires-Dist: pybigquery (==0.4.15)
Requires-Dist: schematics (==2.1.0)
Requires-Dist: pydash (==4.7.4)
Requires-Dist: Unidecode (==1.0.23)
Requires-Dist: networkx (==2.3)
Requires-Dist: xxhash (==1.3.0)
Requires-Dist: antlr4-python3-runtime (==4.8)
Requires-Dist: pydantic (==1.5.1)
Requires-Dist: docstring-parser (==0.7.3)
Requires-Dist: importlib-resources ; python_version < "3.7"
Provides-Extra: dev
Requires-Dist: pytest (>=5.3.5) ; extra == 'dev'
Requires-Dist: responses (>=0.10.14) ; extra == 'dev'
Requires-Dist: freezegun (>=0.3.15) ; extra == 'dev'
Requires-Dist: typing-extensions (>=3.7.4) ; extra == 'dev'
Requires-Dist: mypy (>=0.790) ; extra == 'dev'
Requires-Dist: flake8 (>=3.8.3) ; extra == 'dev'
Requires-Dist: black (==20.8b0) ; extra == 'dev'
Requires-Dist: pre-commit (==2.9.3) ; extra == 'dev'
Provides-Extra: tests
Requires-Dist: pytest (>=5.3.5) ; extra == 'tests'
Requires-Dist: responses (>=0.10.14) ; extra == 'tests'
Requires-Dist: freezegun (>=0.3.15) ; extra == 'tests'
Requires-Dist: typing-extensions (>=3.7.4) ; extra == 'tests'
